LICENSE
MANIFEST.in
README.rst
setup.py
disbi/__init__.py
disbi/admin.py
disbi/apps.py
disbi/cache_table.py
disbi/db_utils.py
disbi/disbimodels.py
disbi/exceptions.py
disbi/experiment_filter.py
disbi/forms.py
disbi/join.py
disbi/models.py
disbi/option_utils.py
disbi/result.py
disbi/utils.py
disbi/validators.py
disbi/views.py
disbi/_import_export/__init__.py
disbi/_import_export/admin.py
disbi/_import_export/django_compat.py
disbi/_import_export/exceptions.py
disbi/_import_export/fields.py
disbi/_import_export/forms.py
disbi/_import_export/instance_loaders.py
disbi/_import_export/models.py
disbi/_import_export/resources.py
disbi/_import_export/results.py
disbi/_import_export/tmp_storages.py
disbi/_import_export/widgets.py
disbi/_import_export/formats/__init__.py
disbi/_import_export/formats/base_formats.py
disbi/migrations/0001_initial.py
disbi/migrations/__init__.py
disbi/static/admin/css/base.css
disbi/static/disbi/css/buttons.dataTables.css
disbi/static/disbi/css/colreorder.dataTables.css
disbi/static/disbi/css/dataTables.css
disbi/static/disbi/css/main.css
disbi/static/disbi/css/main.css.map
disbi/static/disbi/css/ripple.css
disbi/static/disbi/js/data.js
disbi/static/disbi/js/filter.js
disbi/static/disbi/js/jQuery.formset.js
disbi/static/disbi/sass/main.sass
disbi/static/disbi/sass/helpers/_mixins.sass
disbi/static/disbi/sass/helpers/_placeholders.sass
disbi/static/disbi/sass/helpers/_variables.sass
disbi/static/disbi/sass/layout/_grid.sass
disbi/static/disbi/sass/layout/_header.sass
disbi/templates/base.html
disbi/templates/admin/base_site.html
disbi/templates/disbi/data.html
disbi/templates/disbi/filter.html
disbi/templates/disbi/registration/login.html
disbi/templates/disbi/registration/logout.html
disbi/templates/disbi/registration/password_change_done.html
disbi/templates/disbi/registration/password_change_form.html
disbi/templates/disbi/registration/password_reset_complete.html
disbi/templates/disbi/registration/password_reset_confirm.html
django_disbi.egg-info/PKG-INFO
django_disbi.egg-info/SOURCES.txt
django_disbi.egg-info/dependency_links.txt
django_disbi.egg-info/requires.txt
django_disbi.egg-info/top_level.txt