Metadata-Version: 1.1
Name: django-disbi
Version: 0.0.2
Summary: A Django app framework for managing and integrating systems biology data.
Home-page: https://github.com/DISBi/django-disbi
Author: Rüdiger Frederik Busche
Author-email: ruedigerbusche@web.de
License: MIT License
Download-URL: https://github.com/DISBi/django-disbi/archive/0.0.2.tar.gz
Platform: UNKNOWN
Classifier: Environment :: Web Environment
Classifier: Framework :: Django
Classifier: Framework :: Django :: 1.9
Classifier: Intended Audience :: Developers
Classifier: License :: OSI Approved :: MIT License
Classifier: Operating System :: OS Independent
Classifier: Programming Language :: Python
Classifier: Programming Language :: Python :: 3
Classifier: Programming Language :: Python :: 3.4
Classifier: Programming Language :: Python :: 3.5
Classifier: Topic :: Internet :: WWW/HTTP
Classifier: Topic :: Internet :: WWW/HTTP :: Dynamic Content
